pyghmi/__init__.py
pyghmi/constants.py
pyghmi/exceptions.py
pyghmi/media.py
pyghmi/storage.py
pyghmi/version.py
pyghmi/cmd/__init__.py
pyghmi/cmd/fakebmc.py
pyghmi/cmd/pyghmicons.py
pyghmi/cmd/pyghmiutil.py
pyghmi/cmd/virshbmc.py
pyghmi/ipmi/__init__.py
pyghmi/ipmi/bmc.py
pyghmi/ipmi/command.py
pyghmi/ipmi/console.py
pyghmi/ipmi/events.py
pyghmi/ipmi/fru.py
pyghmi/ipmi/sdr.py
pyghmi/ipmi/oem/__init__.py
pyghmi/ipmi/oem/generic.py
pyghmi/ipmi/oem/lookup.py
pyghmi/ipmi/oem/lenovo/__init__.py
pyghmi/ipmi/oem/lenovo/config.py
pyghmi/ipmi/oem/lenovo/cpu.py
pyghmi/ipmi/oem/lenovo/dimm.py
pyghmi/ipmi/oem/lenovo/drive.py
pyghmi/ipmi/oem/lenovo/energy.py
pyghmi/ipmi/oem/lenovo/firmware.py
pyghmi/ipmi/oem/lenovo/handler.py
pyghmi/ipmi/oem/lenovo/imm.py
pyghmi/ipmi/oem/lenovo/inventory.py
pyghmi/ipmi/oem/lenovo/nextscale.py
pyghmi/ipmi/oem/lenovo/pci.py
pyghmi/ipmi/oem/lenovo/psu.py
pyghmi/ipmi/oem/lenovo/raid_controller.py
pyghmi/ipmi/oem/lenovo/raid_drive.py
pyghmi/ipmi/private/__init__.py
pyghmi/ipmi/private/constants.py
pyghmi/ipmi/private/localsession.py
pyghmi/ipmi/private/serversession.py
pyghmi/ipmi/private/session.py
pyghmi/ipmi/private/simplesession.py
pyghmi/ipmi/private/spd.py
pyghmi/ipmi/private/util.py
pyghmi/redfish/__init__.py
pyghmi/redfish/command.py
pyghmi/redfish/oem/__init__.py
pyghmi/redfish/oem/generic.py
pyghmi/redfish/oem/lookup.py
pyghmi/redfish/oem/dell/__init__.py
pyghmi/redfish/oem/dell/idrac.py
pyghmi/redfish/oem/dell/main.py
pyghmi/redfish/oem/lenovo/__init__.py
pyghmi/redfish/oem/lenovo/main.py
pyghmi/redfish/oem/lenovo/smm3.py
pyghmi/redfish/oem/lenovo/tsma.py
pyghmi/redfish/oem/lenovo/xcc.py
pyghmi/redfish/oem/lenovo/xcc3.py
pyghmi/tests/__init__.py
pyghmi/tests/unit/__init__.py
pyghmi/tests/unit/base.py
pyghmi/tests/unit/ipmi/__init__.py
pyghmi/tests/unit/ipmi/test_sdr.py
pyghmi/util/__init__.py
pyghmi/util/parse.py
pyghmi/util/webclient.py
pyghmi-1.6.7.dist-info/AUTHORS
pyghmi-1.6.7.dist-info/LICENSE
pyghmi-1.6.7.dist-info/METADATA
pyghmi-1.6.7.dist-info/WHEEL
pyghmi-1.6.7.dist-info/entry_points.txt
pyghmi-1.6.7.dist-info/pbr.json
pyghmi-1.6.7.dist-info/top_level.txt
pyghmi-1.6.7.dist-info/RECORD
